rejira/__init__.py
rejira-0.0.5.dev1.dist-info/DESCRIPTION.rst
rejira-0.0.5.dev1.dist-info/METADATA
rejira-0.0.5.dev1.dist-info/RECORD
rejira-0.0.5.dev1.dist-info/WHEEL
rejira-0.0.5.dev1.dist-info/metadata.json
rejira-0.0.5.dev1.dist-info/top_level.txt
